ignord/.ignors
ignord/__init__.py
ignord/__main__.py
ignord/cli.py
ignord-0.1.4.dist-info/AUTHORS.rst
ignord-0.1.4.dist-info/LICENSE
ignord-0.1.4.dist-info/METADATA
ignord-0.1.4.dist-info/WHEEL
ignord-0.1.4.dist-info/entry_points.txt
ignord-0.1.4.dist-info/top_level.txt
ignord-0.1.4.dist-info/RECORD
